MANIFEST.in
README.md
requirements.txt
setup.py
test-requirements.txt
talons/__init__.py
talons.auth.oauth.egg-info/PKG-INFO
talons.auth.oauth.egg-info/SOURCES.txt
talons.auth.oauth.egg-info/dependency_links.txt
talons.auth.oauth.egg-info/requires.txt
talons.auth.oauth.egg-info/top_level.txt
talons.auth.oauth.egg-info/zip-safe
talons/auth/__init__.py
talons/auth/oauth/__init__.py
talons/auth/oauth/oauth1.py
tests/__init__.py
tests/test_oauth.py
tests/validator.py