Metadata-Version: 1.1
Name: talons.auth.oauth
Version: 0.0.1
Summary: OAuth 1.0 extension for Talons WSGI middleware library
Home-page: https://github.com/swistakm/talons-oauth
Author: Michał Jaworski
Author-email: swistakm@gmail.com
License: UNKNOWN
Platform: UNKNOWN
Classifier: Development Status :: 4 - Beta
Classifier: Intended Audience :: Developers
Classifier: License :: OSI Approved :: BSD License
Classifier: Operating System :: OS Independent
Classifier: Programming Language :: Python
Classifier: Programming Language :: Python :: 3
